nujson.cpython-38-x86_64-linux-gnu.so
shaped_nujson-1.35.2.dist-info/LICENSE.txt
shaped_nujson-1.35.2.dist-info/RECORD
shaped_nujson-1.35.2.dist-info/top_level.txt
shaped_nujson-1.35.2.dist-info/METADATA
shaped_nujson-1.35.2.dist-info/WHEEL
