Metadata-Version: 2.1
Name: shaped-nujson
Version: 1.35.2
Summary: Ultra fast JSON encoder and decoder for Python with NumPy support
Home-page: https://caiyunapp.com
Download-URL: https://github.com/shaped/ultrajson
Author: caiyunapp
Author-email: admin@caiyunapp.com
License: BSD License
Project-URL: Source, https://github.com/shaped/ultrajson
Keywords: numpy ujson json python3
Platform: any
Classifier: Development Status :: 5 - Production/Stable
Classifier: Intended Audience :: Developers
Classifier: License :: OSI Approved :: BSD License
Classifier: Operating System :: POSIX :: Linux
Classifier: Programming Language :: C
Classifier: Programming Language :: Python :: 3.5
Classifier: Programming Language :: Python :: 3.6
Classifier: Programming Language :: Python :: 3.7
Classifier: Programming Language :: Python :: 3.8
Classifier: Programming Language :: Python :: 3.9
Classifier: Programming Language :: Python :: 3
Requires-Python: >=3.0, !=3.0.*, !=3.1.*, !=3.2.*, !=3.3.*, !=3.4.*
License-File: LICENSE.txt
Requires-Dist: numpy (>=1.16.4)
